{
  "section": "electric",
  "title": "The Cleanroom",
  "stream": [
    {
      "type": "textbox",
      "content": [
        "§oThe Cleanroom is not implemented into GTCEu yet.§r\n\nThe Cleanroom is a well isolated space, with little to no airborne particles, bacteria and other contaminants.\n\nThey will be used for producing nano-scale components of higher tier circuits. The mechanics will not be as punishing as they were in GregTech 5, so stay in touch with us."
      ]
    }
  ],
  "fixed": []
}
